{
    "Language": "Italiano",
    "htmlLangAtt": "it",
    "filewords": {
        "name": "",
        "data": [
            {
                "word": "aiaitcs",
                "x": "4",
                "gameName": "scrabble"
            },
            {
                "word": "otmhre",
                "x": "4",
                "gameName": "scrabble"
            },
            {
                "word": "stuzxawo",
                "x": "4",
                "gameName": "scrabble"
            },
            {
                "word": "white",
                "x": "4",
                "gameName": "scrabble"
            },
            {
                "word": "study",
                "x": "4",
                "gameName": "scrabble"
            },
            {
                "word": "daily",
                "x": "4",
                "gameName": "scrabble"
            },
            {
                "word": "greed",
                "x": "4",
                "gameName": "scrabble"
            },
            {
                "word": "dietp",
                "x": "4",
                "gameName": "scrabble"
            }
        ]
    },
    "filepath": {},
    "title": "Trovare parole di 4 lettere con queste lettere - WordsWithLetters.org",
    "h1": "Trova parole di quattro lettere con queste lettere",
    "h2": "Inserisci le lettere qui sotto per trovare parole di 4 lettere",
    "meta": "Stai ancora pensando a quante parole di quattro lettere puoi fare con queste lettere? Usa il nostro strumento per trovare parole di 4 lettere con queste lettere",
    "featureNo": "02",
    "feature_title": "Features",
    "blogNo": "03",
    "blog_title": "Blog",
    "FaqNo": "04",
    "Faq_title": "FAQ",
    "aboutNo": "05",
    "about_title": "About",
    "featureList": [
        {
            "feature_heading": "Porta una svolta nel tuo gioco. Genera parole di quattro lettere con queste lettere",
            "feature_text": "Spesso questa lettera quattro trova la sua strada nei giochi di parole. Ma la cosa principale è che queste parole con quattro lettere a volte possono avere un punteggio elevato. Tuttavia puoi trovare il tuo salvataggio con il nostro word finder.",
            "fa_class": "/assets/images/star.svg"
        },
        {
            "feature_heading": "Genera parole di quattro lettere con queste lettere",
            "feature_text": "Il nostro wordfinder gratuito ti consente di trovare parole di quattro lettere e aiutarti a vincere la tua partita",
            "fa_class": "/assets/images/star.svg"
        },
        {
            "feature_heading": "Trovare qualsiasi parola numerata con la lettera Four in esso",
            "feature_text": "Il cercatore di parole a quattro lettere ti consente di trovare tutte le parole con quattro lettere fino a 15 caratteri.",
            "fa_class": "/assets/images/star.svg"
        },
        {
            "feature_heading": "Genera anche le parole a quattro lettere più difficili a cui non riesci nemmeno a pensare.",
            "feature_text": "Ottieni un pool di parole di quattro lettere con il punteggio più alto in pochi secondi con il nostro generatore di parole a quattro lettere gratuito.",
            "fa_class": "/assets/images/star.svg"
        }
    ],
    "tags": [],
    "categories": []
}